yta_programming_env/__init__.py
yta_programming_env-0.0.1.dist-info/licenses/LICENSE
yta_programming_env-0.0.1.dist-info/METADATA
yta_programming_env-0.0.1.dist-info/WHEEL
yta_programming_env-0.0.1.dist-info/RECORD
