Metadata-Version: 2.4
Name: yta-programming-env
Version: 0.0.1
Summary: Youtube Autonomous Programming Dependencies Module
License-File: LICENSE
Author: danialcala94
Author-email: danielalcalavalera@gmail.com
Requires-Python: ==3.9
Classifier: Programming Language :: Python :: 3
Classifier: Programming Language :: Python :: 3.9
Requires-Dist: python-dotenv (>=1.0.0,<9.0.0)
Requires-Dist: yta_programming_path (>=0.0.1,<1.0.0)
Requires-Dist: yta_validation (>=0.0.1,<1.0.0)
